ngx_upstream_sentinel/__init__.py
ngx_upstream_sentinel-0.0.6.dist-info/entry_points.txt
ngx_upstream_sentinel-0.0.6.dist-info/LICENSE
ngx_upstream_sentinel-0.0.6.dist-info/WHEEL
ngx_upstream_sentinel-0.0.6.dist-info/METADATA
ngx_upstream_sentinel-0.0.6.dist-info/RECORD
