Metadata-Version: 2.1
Name: ngx-upstream-sentinel
Version: 0.0.6
Summary: 
Author: Rodrigo Pinheiro Matias
Author-email: rodrigopmatias@gmail.com
Requires-Python: >=3.6,<4.0
Classifier: Programming Language :: Python :: 3
Classifier: Programming Language :: Python :: 3.6
Classifier: Programming Language :: Python :: 3.7
Classifier: Programming Language :: Python :: 3.8
Classifier: Programming Language :: Python :: 3.9
Requires-Dist: requests (>=2.25.1,<3.0.0)
